{"flow1_mass_flow": 10000, "flow1_temperature": 20, "flow1_pressure": 4000, "flow1_vapor_phase": 0.9486389593998245, "flow1_molar_flow": 8263, "flow1_volume_flow": 2815, "flow1_molar_enthalpy": 6739, "flow1_mw_avg": 65, "flow1_density_mass": 703, "flow1_z_factor": 0.37430627459567967, "flow1_volume_flow_actual": 4769, "flow1_Cp": 7480, "flow1_Cv": 7488.314, "flow1_Reid_pressure": 7705, "flow1_dew_point_water": -20, "flow1_dew_point_hc": 45, "flow2_mass_flow": 10000, "flow2_temperature": 20, "flow2_pressure": 4000, "flow2_vapor_phase": 0.48600085790198366, "flow2_molar_flow": 7196, "flow2_volume_flow": 918, "flow2_molar_enthalpy": -9112, "flow2_mw_avg": 29, "flow2_density_mass": 606, "flow2_z_factor": 0.45601769380984025, "flow2_volume_flow_actual": 9764, "flow2_Cp": 9191, "flow2_Cv": 9199.314, "flow2_Reid_pressure": 8688, "flow2_dew_point_water": 59, "flow2_dew_point_hc": -94, "flow3_mass_flow": 10000, "flow3_temperature": 20, "flow3_pressure": 4000, "flow3_vapor_phase": 0.5798808597720166, "flow3_molar_flow": 6236, "flow3_volume_flow": 2729, "flow3_molar_enthalpy": -9611, "flow3_mw_avg": 7, "flow3_density_mass": 273, "flow3_z_factor": 0.6843555604136001, "flow3_volume_flow_actual": 9236, "flow3_Cp": 5193, "flow3_Cv": 5201.314, "flow3_Reid_pressure": 71219, "flow3_dew_point_water": -53, "flow3_dew_point_hc": 86, "flow4_mass_flow": 10000, "flow4_temperature": 20, "flow4_pressure": 8200, "flow4_vapor_phase": 0.22171459112474246, "flow4_molar_flow": 7140, "flow4_volume_flow": 6121, "flow4_molar_enthalpy": 8010, "flow4_mw_avg": 227, "flow4_density_mass": 925, "flow4_z_factor": 0.31724297927465195, "flow4_volume_flow_actual": 4636, "flow4_Cp": 995, "flow4_Cv": 1003.314, "flow4_Reid_pressure": 76659, "flow4_dew_point_water": 78, "flow4_dew_point_hc": -45, "flow5_mass_flow": 10000, "flow5_temperature": 10, "flow5_pressure": 8200, "flow5_vapor_phase": 0.6098254514917645, "flow5_molar_flow": 1447, "flow5_volume_flow": 2187, "flow5_molar_enthalpy": -4604, "flow5_mw_avg": 177, "flow5_density_mass": 906, "flow5_z_factor": 0.3381438213262995, "flow5_volume_flow_actual": 3711, "flow5_Cp": 171, "flow5_Cv": 179.314, "flow5_Reid_pressure": 23053, "flow5_dew_point_water": 0, "flow5_dew_point_hc": -29, "flow6_mass_flow": 10000, "flow6_temperature": 10, "flow6_pressure": 2000, "flow6_vapor_phase": 0.38856643929091395, "flow6_molar_flow": 1535, "flow6_volume_flow": 8498, "flow6_molar_enthalpy": -5507, "flow6_mw_avg": 54, "flow6_density_mass": 295, "flow6_z_factor": 0.8387765863929213, "flow6_volume_flow_actual": 2149, "flow6_Cp": 3380, "flow6_Cv": 3388.314, "flow6_Reid_pressure": 43244, "flow6_dew_point_water": 8, "flow6_dew_point_hc": 24, "flow7_mass_flow": 10000, "flow7_temperature": 10, "flow7_pressure": 2000, "flow7_vapor_phase": 0.30570312642198527, "flow7_molar_flow": 4456, "flow7_volume_flow": 1408, "flow7_molar_enthalpy": 7780, "flow7_mw_avg": 225, "flow7_density_mass": 513, "flow7_z_factor": 0.5437162559060309, "flow7_volume_flow_actual": 7292, "flow7_Cp": 6809, "flow7_Cv": 6817.314, "flow7_Reid_pressure": 98890, "flow7_dew_point_water": -41, "flow7_dew_point_hc": -69, "flow8_mass_flow": 10000, "flow8_temperature": 10, "flow8_pressure": 2000, "flow8_vapor_phase": 0.9908214086032868, "flow8_molar_flow": 8652, "flow8_volume_flow": 6548, "flow8_molar_enthalpy": -6926, "flow8_mw_avg": 135, "flow8_density_mass": 357, "flow8_z_factor": 0.6487827787088252, "flow8_volume_flow_actual": 188, "flow8_Cp": 8124, "flow8_Cv": 8132.314, "flow8_Reid_pressure": 35366, "flow8_dew_point_water": 53, "flow8_dew_point_hc": 43, "flow9_mass_flow": 10000, "flow9_temperature": 10, "flow9_pressure": 2000, "flow9_vapor_phase": 0.585120372385007, "flow9_molar_flow": 5415, "flow9_volume_flow": 1703, "flow9_molar_enthalpy": 2558, "flow9_mw_avg": 127, "flow9_density_mass": 487, "flow9_z_factor": 0.6128773506182936, "flow9_volume_flow_actual": 663, "flow9_Cp": 8875, "flow9_Cv": 8883.314, "flow9_Reid_pressure": 35611, "flow9_dew_point_water": 97, "flow9_dew_point_hc": -26, "separator2f1_pressure_drop": 0, "compressor1_key_value": 8200, "compressor1_key_value_type": "pressure_out", "compressor1_efficiency_value": 75, "compressor1_efficiency_type": "adiabatic", "compressor1_delta_pressure": 4200, "compressor1_compress_ratio": 2.05, "compressor1_duty": 8317, "compressor1_head_poly": 1804, "compressor1_head_adi": 6292, "compressor1_efficiency_poly": 35, "compressor1_efficiency_adi": 75, "compressor1_polytropic_exp": 11, "compressor1_adiabatic_exp": 29, "chiller1_delta_T": -10, "chiller1_duty": 216, "valve1_pressure_drop": 6200, "separator3f1_pressure_drop": 0}